[
	{
		"item_section": "Water",
		"item_id": "76379",
		"item_name": "Aussie Natural 15 Ltr Water Dispenser*",
		"item_supplier": "Liquor Barons Kenwick (LIQU000)",
		"item_price": "75.00",
		"item_par_level": 0,
		"item_qty_step": 0,
		"item_image": "/items/76379/image?style=detail",
		"item_part_number": "38893",
		"item_active": "0.00",
		"cart_response": false,
		"cart_text": "Updating Basket",
		"cart_success": false
	},
	{
		"item_section": "Water",
		"item_id": "3531",
		"item_name": "JT's Coconut Water Cans 510ml Ctn (24)*",
		"item_supplier": "Liquor Barons Kenwick (LIQU000)",
		"item_price": "57.20",
		"item_par_level": 0,
		"item_qty_step": 0,
		"item_image": "/items/3531/image?style=detail",
		"item_part_number": "39561",
		"item_active": "0.00",
		"cart_response": false,
		"cart_text": "Updating Basket",
		"cart_success": false
	},
	{
		"item_section": "Water",
		"item_id": "3532",
		"item_name": "H2 Coconut Water Soft Pack 1000ml Ctn (6)*",
		"item_supplier": "Liquor Barons Kenwick (LIQU000)",
		"item_price": "36.00",
		"item_par_level": 0,
		"item_qty_step": 0,
		"item_image": "/items/3532/image?style=detail",
		"item_part_number": "39563",
		"item_active": "0.00",
		"cart_response": false,
		"cart_text": "Updating Basket",
		"cart_success": false
	},
	{
		"item_section": "Water",
		"item_id": "76381",
		"item_name": "San Pellegrino Mineral Water 1000ml Ctn (12)*",
		"item_supplier": "Liquor Barons Kenwick (LIQU000)",
		"item_price": "30.64",
		"item_par_level": 0,
		"item_qty_step": 0,
		"item_image": "/items/76381/image?style=detail",
		"item_part_number": "39761",
		"item_active": "0.00",
		"cart_response": false,
		"cart_text": "Updating Basket",
		"cart_success": false
	},
	{
		"item_section": "Water",
		"item_id": "76380",
		"item_name": "Mt Franklin Still Mineral Water 330ml Ctn (24)",
		"item_supplier": "Liquor Barons Kenwick (LIQU000)",
		"item_price": "31.10",
		"item_par_level": 0,
		"item_qty_step": 0,
		"item_image": "/items/76380/image?style=detail",
		"item_part_number": "39990",
		"item_active": "Not available",
		"cart_response": false,
		"cart_text": "Updating Basket",
		"cart_success": false
	},
	{
		"item_section": "Water",
		"item_id": "76376",
		"item_name": "Capi Soda Water 250ml Ctn (24)*",
		"item_supplier": "Liquor Barons Kenwick (LIQU000)",
		"item_price": "45.18",
		"item_par_level": 0,
		"item_qty_step": 0,
		"item_image": "/items/76376/image?style=detail",
		"item_part_number": "40014",
		"item_active": "0.00",
		"cart_response": false,
		"cart_text": "Updating Basket",
		"cart_success": false
	},
	{
		"item_section": "Water",
		"item_id": "76375",
		"item_name": "Capi Tonic Water 250ml Ctn (24)*",
		"item_supplier": "Liquor Barons Kenwick (LIQU000)",
		"item_price": "45.18",
		"item_par_level": 0,
		"item_qty_step": 0,
		"item_image": "/items/76375/image?style=detail",
		"item_part_number": "38185",
		"item_active": "0.00",
		"cart_response": false,
		"cart_text": "Updating Basket",
		"cart_success": false
	},
	{
		"item_section": "Water",
		"item_id": "30802",
		"item_name": "San Pellegrino Spark Water 1000ml Ctn (12)*",
		"item_supplier": "Liquor Barons Kenwick (LIQU000)",
		"item_price": "24.60",
		"item_par_level": 0,
		"item_qty_step": 0,
		"item_image": "/items/30802/image?style=detail",
		"item_part_number": "Liquor Barons Kenwick (LIQU000)",
		"item_active": "0.00",
		"cart_response": false,
		"cart_text": "Updating Basket",
		"cart_success": false
	},
	{
		"item_section": "Water",
		"item_id": "30797",
		"item_name": "Capi Sparkling Mineral Water 250ml Ctn (24)",
		"item_supplier": "Liquor Barons Kenwick (LIQU000)",
		"item_price": "33.18",
		"item_par_level": 0,
		"item_qty_step": 0,
		"item_image": "/items/30797/image?style=detail",
		"item_part_number": "39753",
		"item_active": "0.00",
		"cart_response": false,
		"cart_text": "Updating Basket",
		"cart_success": false
	},
	{
		"item_section": "Water",
		"item_id": "3528",
		"item_name": "San Pellegrino Mineral Water 250ml Ctn (24)*",
		"item_supplier": "Liquor Barons Kenwick (LIQU000)",
		"item_price": "29.55",
		"item_par_level": 0,
		"item_qty_step": 0,
		"item_image": "/items/3528/image?style=detail",
		"item_part_number": "39091",
		"item_active": "0.00",
		"cart_response": false,
		"cart_text": "Updating Basket",
		"cart_success": false
	},
	{
		"item_section": "Water",
		"item_id": "30796",
		"item_name": "Capi Tonic Water 250ml Ctn (24)",
		"item_supplier": "Liquor Barons Kenwick (LIQU000)",
		"item_price": "36.27",
		"item_par_level": 0,
		"item_qty_step": 0,
		"item_image": "/items/30796/image?style=detail",
		"item_part_number": "39752",
		"item_active": "0.00",
		"cart_response": false,
		"cart_text": "Updating Basket",
		"cart_success": false
	},
	{
		"item_section": "Water",
		"item_id": "30799",
		"item_name": "Mt Franklin Lightly Spark Water 1250ml Ctn(12)",
		"item_supplier": "Liquor Barons Kenwick (LIQU000)",
		"item_price": "28.09",
		"item_par_level": 0,
		"item_qty_step": 0,
		"item_image": "/items/30799/image?style=detail",
		"item_part_number": "39755",
		"item_active": "0.00",
		"cart_response": false,
		"cart_text": "Updating Basket",
		"cart_success": false
	},
	{
		"item_section": "Water",
		"item_id": "3527",
		"item_name": "Mt Franklin Sparkling Water 450ml Ctn (24)*",
		"item_supplier": "Liquor Barons Kenwick (LIQU000)",
		"item_price": "43.55",
		"item_par_level": 0,
		"item_qty_step": 0,
		"item_image": "/items/3527/image?style=detail",
		"item_part_number": "39551",
		"item_active": "0.00",
		"cart_response": false,
		"cart_text": "Updating Basket",
		"cart_success": false
	},
	{
		"item_section": "Water",
		"item_id": "3526",
		"item_name": "Mt Franklin Spring Water 600ml Ctn (24)",
		"item_supplier": "Liquor Barons Kenwick (LIQU000)",
		"item_price": "17.80",
		"item_par_level": 0,
		"item_qty_step": 0,
		"item_image": "/items/3526/image?style=detail",
		"item_part_number": "39553",
		"item_active": "0.00",
		"cart_response": false,
		"cart_text": "Updating Basket",
		"cart_success": false
	},
	{
		"item_section": "Water",
		"item_id": "3525",
		"item_name": "Aussie Narural Spring Water Pallet 600ml (60)",
		"item_supplier": "Liquor Barons Kenwick (LIQU000)",
		"item_price": "470.00",
		"item_par_level": 0,
		"item_qty_step": 0,
		"item_image": "/items/3525/image?style=detail",
		"item_part_number": "38894",
		"item_active": "0.00",
		"cart_response": false,
		"cart_text": "Updating Basket",
		"cart_success": false
	},
	{
		"item_section": "Water",
		"item_id": "3524",
		"item_name": "Aussie Natural Spring Water 600ml Ctn (24)",
		"item_supplier": "Liquor Barons Kenwick (LIQU000)",
		"item_price": "8.00",
		"item_par_level": 0,
		"item_qty_step": 0,
		"item_image": "/items/3524/image?style=detail",
		"item_part_number": "38208",
		"item_active": "0.00",
		"cart_response": false,
		"cart_text": "Updating Basket",
		"cart_success": false
	},
	{
		"item_section": "Water",
		"item_id": "3523",
		"item_name": "Aussie Natural Spring Water 1.5 Ltr Ctn (8)",
		"item_supplier": "Liquor Barons Kenwick (LIQU000)",
		"item_price": "6.75",
		"item_par_level": 0,
		"item_qty_step": 0,
		"item_image": "/items/3523/image?style=detail",
		"item_part_number": "38211",
		"item_active": "0.00",
		"cart_response": false,
		"cart_text": "Updating Basket",
		"cart_success": false
	},
	{
		"item_section": "Water",
		"item_id": "3522",
		"item_name": "Aussie Natural Water 15Ltr",
		"item_supplier": "Liquor Barons Kenwick (LIQU000)",
		"item_price": "8.00",
		"item_par_level": 0,
		"item_qty_step": 0,
		"item_image": "/items/3522/image?style=detail",
		"item_part_number": "38560",
		"item_active": "0.00",
		"cart_response": false,
		"cart_text": "Updating Basket",
		"cart_success": false
	},
	{
		"item_section": "Water",
		"item_id": "3521",
		"item_name": "Aussie Natural Water 15Ltr Pallet (50)",
		"item_supplier": "Liquor Barons Kenwick (LIQU000)",
		"item_price": "375.00",
		"item_par_level": 0,
		"item_qty_step": 0,
		"item_image": "/items/3521/image?style=detail",
		"item_part_number": "38741",
		"item_active": "0.00",
		"cart_response": false,
		"cart_text": "Updating Basket",
		"cart_success": false
	},
	{
		"item_section": "Energy Drink",
		"item_id": "76374",
		"item_name": "Maximus Sports Drink Red 1000ml Ctn (12)*",
		"item_supplier": "Liquor Barons Kenwick (LIQU000)",
		"item_price": "28.27",
		"item_par_level": 0,
		"item_qty_step": 0,
		"item_image": "/items/76374/image?style=detail",
		"item_part_number": "40005",
		"item_active": "0.00",
		"cart_response": false,
		"cart_text": "Updating Basket",
		"cart_success": false
	},
	{
		"item_section": "Energy Drink",
		"item_id": "3513",
		"item_name": "V Energy Drink Cans 250ml Ctn (24)*",
		"item_supplier": "Liquor Barons Kenwick (LIQU000)",
		"item_price": "42.91",
		"item_par_level": 0,
		"item_qty_step": 0,
		"item_image": "/items/3513/image?style=detail",
		"item_part_number": "38455",
		"item_active": "0.00",
		"cart_response": false,
		"cart_text": "Updating Basket",
		"cart_success": false
	},
	{
		"item_section": "Energy Drink",
		"item_id": "76373",
		"item_name": "Maximus Sports Drink Blue 1000ml Ctn (12)*",
		"item_supplier": "Liquor Barons Kenwick (LIQU000)",
		"item_price": "28.27",
		"item_par_level": 0,
		"item_qty_step": 0,
		"item_image": "/items/76373/image?style=detail",
		"item_part_number": "40003",
		"item_active": "0.00",
		"cart_response": false,
		"cart_text": "Updating Basket",
		"cart_success": false
	},
	{
		"item_section": "Energy Drink",
		"item_id": "76377",
		"item_name": "Red Bull Energy Drink Cans 473ml Ctn (12)*",
		"item_supplier": "Liquor Barons Kenwick (LIQU000)",
		"item_price": "36.45",
		"item_par_level": 0,
		"item_qty_step": 0,
		"item_image": "/items/76377/image?style=detail",
		"item_part_number": "39975",
		"item_active": "0.00",
		"cart_response": false,
		"cart_text": "Updating Basket",
		"cart_success": false
	},
	{
		"item_section": "Energy Drink",
		"item_id": "3510",
		"item_name": "Red Bull Energy Drink Cans 250ml Ctn (24)*",
		"item_supplier": "Liquor Barons Kenwick (LIQU000)",
		"item_price": "49.09",
		"item_par_level": 0,
		"item_qty_step": 0,
		"item_image": "/items/3510/image?style=detail",
		"item_part_number": "11447",
		"item_active": "0.00",
		"cart_response": false,
		"cart_text": "Updating Basket",
		"cart_success": false
	},
	{
		"item_section": "Energy Drink",
		"item_id": "3511",
		"item_name": "Red Bull Sugar Free Cans 250ml Ctn (24)*",
		"item_supplier": "Liquor Barons Kenwick (LIQU000)",
		"item_price": "49.09",
		"item_par_level": 0,
		"item_qty_step": 0,
		"item_image": "/items/3511/image?style=detail",
		"item_part_number": "38240",
		"item_active": "0.00",
		"cart_response": false,
		"cart_text": "Updating Basket",
		"cart_success": false
	},
	{
		"item_section": "Energy Drink",
		"item_id": "3512",
		"item_name": "V Energy Drink Cans 500ml Ctn (24)*",
		"item_supplier": "Liquor Barons Kenwick (LIQU000)",
		"item_price": "63.36",
		"item_par_level": 0,
		"item_qty_step": 0,
		"item_image": "/items/3512/image?style=detail",
		"item_part_number": "38394",
		"item_active": "0.00",
		"cart_response": false,
		"cart_text": "Updating Basket",
		"cart_success": false
	},
	{
		"item_section": "Energy Drink",
		"item_id": "3509",
		"item_name": "Mother Energy Cans 500ml Ctn (24)*",
		"item_supplier": "Liquor Barons Kenwick (LIQU000)",
		"item_price": "45.18",
		"item_par_level": 0,
		"item_qty_step": 0,
		"item_image": "/items/3509/image?style=detail",
		"item_part_number": "38250",
		"item_active": "0.00",
		"cart_response": false,
		"cart_text": "Updating Basket",
		"cart_success": false
	},
	{
		"item_section": "Energy Drink",
		"item_id": "3496",
		"item_name": "Powerade Orange 600ml Ctn (12)",
		"item_supplier": "Liquor Barons Kenwick (LIQU000)",
		"item_price": "27.82",
		"item_par_level": 0,
		"item_qty_step": 0,
		"item_image": "/items/3496/image?style=detail",
		"item_part_number": "38664",
		"item_active": "0.00",
		"cart_response": false,
		"cart_text": "Updating Basket",
		"cart_success": false
	},
	{
		"item_section": "Energy Drink",
		"item_id": "3495",
		"item_name": "Powerade Lemon Lime 600ml Ctn (12)",
		"item_supplier": "Liquor Barons Kenwick (LIQU000)",
		"item_price": "27.82",
		"item_par_level": 0,
		"item_qty_step": 0,
		"item_image": "/items/3495/image?style=detail",
		"item_part_number": "38662",
		"item_active": "0.00",
		"cart_response": false,
		"cart_text": "Updating Basket",
		"cart_success": false
	},
	{
		"item_section": "Energy Drink",
		"item_id": "3494",
		"item_name": "Powerade Berry Ice 600ml Ctn 600ml (12)",
		"item_supplier": "Liquor Barons Kenwick (LIQU000)",
		"item_price": "27.82",
		"item_par_level": 0,
		"item_qty_step": 0,
		"item_image": "/items/3494/image?style=detail",
		"item_part_number": "38660",
		"item_active": "0.00",
		"cart_response": false,
		"cart_text": "Updating Basket",
		"cart_success": false
	},
	{
		"item_section": "Energy Drink",
		"item_id": "3492",
		"item_name": "Gatorade Orange Ice 600ml Ctn (12)*",
		"item_supplier": "Liquor Barons Kenwick (LIQU000)",
		"item_price": "35.27",
		"item_par_level": 0,
		"item_qty_step": 0,
		"item_image": "/items/3492/image?style=detail",
		"item_part_number": "38575",
		"item_active": "0.00",
		"cart_response": false,
		"cart_text": "Updating Basket",
		"cart_success": false
	},
	{
		"item_section": "Energy Drink",
		"item_id": "3491",
		"item_name": "Gatorade Berry Chill 600ml Ctn (12)*",
		"item_supplier": "Liquor Barons Kenwick (LIQU000)",
		"item_price": "35.27",
		"item_par_level": 0,
		"item_qty_step": 0,
		"item_image": "/items/3491/image?style=detail",
		"item_part_number": "38244",
		"item_active": "0.00",
		"cart_response": false,
		"cart_text": "Updating Basket",
		"cart_success": false
	},
	{
		"item_section": "Energy Drink",
		"item_id": "3493",
		"item_name": "Powerade Mountain Blast Blue 600ml Ctn (12)",
		"item_supplier": "Liquor Barons Kenwick (LIQU000)",
		"item_price": "27.82",
		"item_par_level": 0,
		"item_qty_step": 0,
		"item_image": "/items/3493/image?style=detail",
		"item_part_number": "38658",
		"item_active": "0.00",
		"cart_response": false,
		"cart_text": "Updating Basket",
		"cart_success": false
	},
	{
		"item_section": "Energy Drink",
		"item_id": "3490",
		"item_name": "Gatorade Lemon Lime 600ml Ctn (12)*",
		"item_supplier": "Liquor Barons Kenwick (LIQU000)",
		"item_price": "35.27",
		"item_par_level": 0,
		"item_qty_step": 0,
		"item_image": "/items/3490/image?style=detail",
		"item_part_number": "38248",
		"item_active": "0.00",
		"cart_response": false,
		"cart_text": "Updating Basket",
		"cart_success": false
	},
	{
		"item_section": "Energy Drink",
		"item_id": "3489",
		"item_name": "Gatorade Blue Ice 600ml Ctn (12)*",
		"item_supplier": "Liquor Barons Kenwick (LIQU000)",
		"item_price": "35.27",
		"item_par_level": 0,
		"item_qty_step": 0,
		"item_image": "/items/3489/image?style=detail",
		"item_part_number": "38212",
		"item_active": "0.00",
		"cart_response": false,
		"cart_text": "Updating Basket",
		"cart_success": false
	},
	{
		"item_section": "Soft Drink",
		"item_id": "30801",
		"item_name": "Sprite Lemonade Bottles 390ml Ctn (24)",
		"item_supplier": "Liquor Barons Kenwick (LIQU000)",
		"item_price": "40.00",
		"item_par_level": 0,
		"item_qty_step": 0,
		"item_image": "/items/30801/image?style=detail",
		"item_part_number": "39757",
		"item_active": "0.00",
		"cart_response": false,
		"cart_text": "Updating Basket",
		"cart_success": false
	},
	{
		"item_section": "Soft Drink",
		"item_id": "30800",
		"item_name": "Diet Coca Cola Bottles 390ml Ctn (24)*",
		"item_supplier": "Liquor Barons Kenwick (LIQU000)",
		"item_price": "43.00",
		"item_par_level": 0,
		"item_qty_step": 0,
		"item_image": "/items/30800/image?style=detail",
		"item_part_number": "39756",
		"item_active": "0.00",
		"cart_response": false,
		"cart_text": "Updating Basket",
		"cart_success": false
	},
	{
		"item_section": "Soft Drink",
		"item_id": "30798",
		"item_name": "Coca Cola Bottles 390ml Ctn (24)",
		"item_supplier": "Liquor Barons Kenwick (LIQU000)",
		"item_price": "43.00",
		"item_par_level": 0,
		"item_qty_step": 0,
		"item_image": "/items/30798/image?style=detail",
		"item_part_number": "39754",
		"item_active": "0.00",
		"cart_response": false,
		"cart_text": "Updating Basket",
		"cart_success": false
	},
	{
		"item_section": "Soft Drink",
		"item_id": "3520",
		"item_name": "Bundaberg Ginger Beer 375ml Ctn (24)*",
		"item_supplier": "Liquor Barons Kenwick (LIQU000)",
		"item_price": "31.73",
		"item_par_level": 0,
		"item_qty_step": 0,
		"item_image": "/items/3520/image?style=detail",
		"item_part_number": "12690",
		"item_active": "0.00",
		"cart_response": false,
		"cart_text": "Updating Basket",
		"cart_success": false
	},
	{
		"item_section": "Soft Drink",
		"item_id": "3515",
		"item_name": "Deep Springe Orange Pass Cans 375ml Ctn (24)*",
		"item_supplier": "Liquor Barons Kenwick (LIQU000)",
		"item_price": "25.09",
		"item_par_level": 0,
		"item_qty_step": 0,
		"item_image": "/items/3515/image?style=detail",
		"item_part_number": "38251",
		"item_active": "0.00",
		"cart_response": false,
		"cart_text": "Updating Basket",
		"cart_success": false
	},
	{
		"item_section": "Soft Drink",
		"item_id": "3514",
		"item_name": "Deep Spring Lm Lime Cans 375ml Ctn (24)*",
		"item_supplier": "Liquor Barons Kenwick (LIQU000)",
		"item_price": "25.09",
		"item_par_level": 0,
		"item_qty_step": 0,
		"item_image": "/items/3514/image?style=detail",
		"item_part_number": "38253",
		"item_active": "0.00",
		"cart_response": false,
		"cart_text": "Updating Basket",
		"cart_success": false
	},
	{
		"item_section": "Soft Drink",
		"item_id": "3508",
		"item_name": "Schweppes Soda Water1.1 Ltr Ctn (12)*",
		"item_supplier": "Liquor Barons Kenwick (LIQU000)",
		"item_price": "23.55",
		"item_par_level": 0,
		"item_qty_step": 0,
		"item_image": "/items/3508/image?style=detail",
		"item_part_number": "38353",
		"item_active": "0.00",
		"cart_response": false,
		"cart_text": "Updating Basket",
		"cart_success": false
	},
	{
		"item_section": "Soft Drink",
		"item_id": "3507",
		"item_name": "Schweppes Soda Water 300ml Ctn (24)*",
		"item_supplier": "Liquor Barons Kenwick (LIQU000)",
		"item_price": "42.82",
		"item_par_level": 0,
		"item_qty_step": 0,
		"item_image": "/items/3507/image?style=detail",
		"item_part_number": "2619",
		"item_active": "0.00",
		"cart_response": false,
		"cart_text": "Updating Basket",
		"cart_success": false
	},
	{
		"item_section": "Soft Drink",
		"item_id": "3506",
		"item_name": "Sprite Lemonade Cans 375ml Ctn (24)*",
		"item_supplier": "Liquor Barons Kenwick (LIQU000)",
		"item_price": "20.73",
		"item_par_level": 0,
		"item_qty_step": 0,
		"item_image": "/items/3506/image?style=detail",
		"item_part_number": "38216",
		"item_active": "0.00",
		"cart_response": false,
		"cart_text": "Updating Basket",
		"cart_success": false
	},
	{
		"item_section": "Soft Drink",
		"item_id": "3505",
		"item_name": "Lift Cans 375ml Ctn (24)*",
		"item_supplier": "Liquor Barons Kenwick (LIQU000)",
		"item_price": "20.73",
		"item_par_level": 0,
		"item_qty_step": 0,
		"item_image": "/items/3505/image?style=detail",
		"item_part_number": "38214",
		"item_active": "0.00",
		"cart_response": false,
		"cart_text": "Updating Basket",
		"cart_success": false
	},
	{
		"item_section": "Soft Drink",
		"item_id": "3504",
		"item_name": "Kirks Pasito Pasito Cans 375ml Ctn (24)*",
		"item_supplier": "Liquor Barons Kenwick (LIQU000)",
		"item_price": "20.73",
		"item_par_level": 0,
		"item_qty_step": 0,
		"item_image": "/items/3504/image?style=detail",
		"item_part_number": "38397",
		"item_active": "0.00",
		"cart_response": false,
		"cart_text": "Updating Basket",
		"cart_success": false
	},
	{
		"item_section": "Soft Drink",
		"item_id": "3503",
		"item_name": "Kirks Kole Beer Cans 375ml Ctn (24)*",
		"item_supplier": "Liquor Barons Kenwick (LIQU000)",
		"item_price": "20.73",
		"item_par_level": 0,
		"item_qty_step": 0,
		"item_image": "/items/3503/image?style=detail",
		"item_part_number": "38218",
		"item_active": "0.00",
		"cart_response": false,
		"cart_text": "Updating Basket",
		"cart_success": false
	},
	{
		"item_section": "Soft Drink",
		"item_id": "3502",
		"item_name": "Kirks Ginger Beer Cans 375ml Ctn (24)*",
		"item_supplier": "Liquor Barons Kenwick (LIQU000)",
		"item_price": "20.73",
		"item_par_level": 0,
		"item_qty_step": 0,
		"item_image": "/items/3502/image?style=detail",
		"item_part_number": "38220",
		"item_active": "0.00",
		"cart_response": false,
		"cart_text": "Updating Basket",
		"cart_success": false
	},
	{
		"item_section": "Soft Drink",
		"item_id": "3501",
		"item_name": "Kirks Club Lemon Cans 375ml Ctn (24)*",
		"item_supplier": "Liquor Barons Kenwick (LIQU000)",
		"item_price": "20.73",
		"item_par_level": 0,
		"item_qty_step": 0,
		"item_image": "/items/3501/image?style=detail",
		"item_part_number": "38580",
		"item_active": "0.00",
		"cart_response": false,
		"cart_text": "Updating Basket",
		"cart_success": false
	},
	{
		"item_section": "Soft Drink",
		"item_id": "3500",
		"item_name": "Fanta Orange Cans 375ml Ctn (24)*",
		"item_supplier": "Liquor Barons Kenwick (LIQU000)",
		"item_price": "20.73",
		"item_par_level": 0,
		"item_qty_step": 0,
		"item_image": "/items/3500/image?style=detail",
		"item_part_number": "38081",
		"item_active": "0.00",
		"cart_response": false,
		"cart_text": "Updating Basket",
		"cart_success": false
	},
	{
		"item_section": "Soft Drink",
		"item_id": "3499",
		"item_name": "Diet Coca Cola Cans 375ml Ctn (24)*",
		"item_supplier": "Liquor Barons Kenwick (LIQU000)",
		"item_price": "20.73",
		"item_par_level": 0,
		"item_qty_step": 0,
		"item_image": "/items/3499/image?style=detail",
		"item_part_number": "2597",
		"item_active": "0.00",
		"cart_response": false,
		"cart_text": "Updating Basket",
		"cart_success": false
	},
	{
		"item_section": "Soft Drink",
		"item_id": "3498",
		"item_name": "Coca Cola No Sugar Cans 375ml Ctn (24)*",
		"item_supplier": "Liquor Barons Kenwick (LIQU000)",
		"item_price": "20.73",
		"item_par_level": 0,
		"item_qty_step": 0,
		"item_image": "/items/3498/image?style=detail",
		"item_part_number": "27885",
		"item_active": "0.00",
		"cart_response": false,
		"cart_text": "Updating Basket",
		"cart_success": false
	},
	{
		"item_section": "Soft Drink",
		"item_id": "3497",
		"item_name": "Coca Cola Cans 375ml Ctn (24)*",
		"item_supplier": "Liquor Barons Kenwick (LIQU000)",
		"item_price": "20.73",
		"item_par_level": 0,
		"item_qty_step": 0,
		"item_image": "/items/3497/image?style=detail",
		"item_part_number": "2587",
		"item_active": "0.00",
		"cart_response": false,
		"cart_text": "Updating Basket",
		"cart_success": false
	},
	{
		"item_section": "Soft Drink",
		"item_id": "76378",
		"item_name": "V Energy Drink Blue Cans 500ml Ctn (24)*",
		"item_supplier": "Liquor Barons Kenwick (LIQU000)",
		"item_price": "31.73",
		"item_par_level": 0,
		"item_qty_step": 0,
		"item_image": "/items/76378/image?style=detail",
		"item_part_number": "40007",
		"item_active": "0.00",
		"cart_response": false,
		"cart_text": "Updating Basket",
		"cart_success": false
	},
	{
		"item_section": "Tea",
		"item_id": "3519",
		"item_name": "Lipton Ice Tea Raspberry 500ml Ctn (12)*",
		"item_supplier": "Liquor Barons Kenwick (LIQU000)",
		"item_price": "26.00",
		"item_par_level": 0,
		"item_qty_step": 0,
		"item_image": "/items/3519/image?style=detail",
		"item_part_number": "39206",
		"item_active": "0.00",
		"cart_response": false,
		"cart_text": "Updating Basket",
		"cart_success": false
	},
	{
		"item_section": "Tea",
		"item_id": "3518",
		"item_name": "Lipton Ice Tea Peach 500ml Ctn (12)*",
		"item_supplier": "Liquor Barons Kenwick (LIQU000)",
		"item_price": "26.00",
		"item_par_level": 0,
		"item_qty_step": 0,
		"item_image": "/items/3518/image?style=detail",
		"item_part_number": "39204",
		"item_active": "0.00",
		"cart_response": false,
		"cart_text": "Updating Basket",
		"cart_success": false
	},
	{
		"item_section": "Tea",
		"item_id": "3517",
		"item_name": "Lipton Ice Tea Mango 500ml Ctn (12)*",
		"item_supplier": "Liquor Barons Kenwick (LIQU000)",
		"item_price": "26.00",
		"item_par_level": 0,
		"item_qty_step": 0,
		"item_image": "/items/3517/image?style=detail",
		"item_part_number": "39205",
		"item_active": "0.00",
		"cart_response": false,
		"cart_text": "Updating Basket",
		"cart_success": false
	},
	{
		"item_section": "Tea",
		"item_id": "3516",
		"item_name": "Lipton Ice Tea Lemon 500ml Ctn (12)*",
		"item_supplier": "Liquor Barons Kenwick (LIQU000)",
		"item_price": "26.00",
		"item_par_level": 0,
		"item_qty_step": 0,
		"item_image": "/items/3516/image?style=detail",
		"item_part_number": "39203",
		"item_active": "0.00",
		"cart_response": false,
		"cart_text": "Updating Basket",
		"cart_success": false
	},
	{
		"item_section": "Other",
		"item_id": "3530",
		"item_name": "Harvey Fresh Apple Juice 250ml Ctn (24)",
		"item_supplier": "Liquor Barons Kenwick (LIQU000)",
		"item_price": "15.50",
		"item_par_level": 0,
		"item_qty_step": 0,
		"item_image": "/items/3530/image?style=detail",
		"item_part_number": "38202",
		"item_active": "0.00",
		"cart_response": false,
		"cart_text": "Updating Basket",
		"cart_success": false
	},
	{
		"item_section": "Other",
		"item_id": "3529",
		"item_name": "Harvey Fresh Orange Juice 250ml Ctn (24)",
		"item_supplier": "Liquor Barons Kenwick (LIQU000)",
		"item_price": "15.50",
		"item_par_level": 0,
		"item_qty_step": 0,
		"item_image": "/items/3529/image?style=detail",
		"item_part_number": "38200",
		"item_active": "0.00",
		"cart_response": false,
		"cart_text": "Updating Basket",
		"cart_success": false
	}
]